MANIFEST.in
README.md
requirements.txt
setup.cfg
setup.py
two_factor_auth/__init__.py
two_factor_auth/admin.py
two_factor_auth/apps.py
two_factor_auth/forms.py
two_factor_auth/models.py
two_factor_auth/permissions.py
two_factor_auth/serializers.py
two_factor_auth/signals.py
two_factor_auth/strings.py
two_factor_auth/tests.py
two_factor_auth/urls.py
two_factor_auth/utils.py
two_factor_auth/templates/two_factor_auth/_base.html
two_factor_auth/templates/two_factor_auth/_base_focus.html
two_factor_auth/templates/two_factor_auth/_wizard_actions.html
two_factor_auth/templates/two_factor_auth/_wizard_forms.html
two_factor_auth/templates/two_factor_auth/admin/config.html
two_factor_auth/templates/two_factor_auth/core/2fa_required.html
two_factor_auth/templates/two_factor_auth/core/backup_tokens.html
two_factor_auth/templates/two_factor_auth/core/login.html
two_factor_auth/templates/two_factor_auth/core/setup.html
two_factor_auth/templates/two_factor_auth/core/setup_complete.html
two_factor_auth/templates/two_factor_auth/profile/disable.html
two_factor_auth/templates/two_factor_auth/profile/profile.html
two_factor_auth_olaii.egg-info/PKG-INFO
two_factor_auth_olaii.egg-info/SOURCES.txt
two_factor_auth_olaii.egg-info/dependency_links.txt
two_factor_auth_olaii.egg-info/requires.txt
two_factor_auth_olaii.egg-info/top_level.txt