Metadata-Version: 1.1
Name: two-factor-auth-olaii
Version: 1.1
Summary: Two-factor authentication for Django based on django-two-factor-auth and deux.
Home-page: https://gitlab.xlab.si/olaii/Olaii_2FA
Author: Polona Remic
Author-email: polona@olaii.com
License: UNKNOWN
Download-URL: https://gitlab.xlab.si/olaii/Olaii_2FA
Keywords: django,two-factor authentication
Platform: UNKNOWN
